super_vv/__init__.py
super_vv/core.py
super_vv/experimental.py
super_vv/nn.py
super_x/__init__.py
super_x/broadcast.py
super_x/core.py
super_x/linalg.py
super_x/random.py
superpof-0.0.1.dist-info/METADATA
superpof-0.0.1.dist-info/WHEEL
superpof-0.0.1.dist-info/top_level.txt
superpof-0.0.1.dist-info/RECORD
