Metadata-Version: 2.4
Name: superpof
Version: 0.0.1
Summary: Una librería super beta inspirada en NumPy y Torch pero simplificada
Home-page: https://github.com/tuusuario/super_b
Author: Tu Nombre
Author-email: tunombre@example.com
Requires-Python: >=3.8
Dynamic: author
Dynamic: author-email
Dynamic: description
Dynamic: description-content-type
Dynamic: home-page
Dynamic: requires-python
Dynamic: summary
